vectorops/__init__.py
vectorops/constants.py
vectorops/dataset_manager.py
vectorops/datasets.py
vectorops/projection/comparator.py
vectorops/projection/distplot.py
vectorops/projection/radar.py
vectorops/projection/scatter.py
vectorops/projection_manager.py
vectorops/utils/__init__.py
vectorops/utils/distance_utils.py
vectorops/utils/encode_utils.py
vectorops/utils/formulae_utils.py
vectorops/utils/nn_utils.py
vectorops/utils/plot_utils.py
relevanceai_vectorops-0.1.2.dist-info/WHEEL
relevanceai_vectorops-0.1.2.dist-info/METADATA
relevanceai_vectorops-0.1.2.dist-info/RECORD
