Metadata-Version: 2.1
Name: relevanceai-vectorops
Version: 0.1.2
Summary: Vector Ops Exploration and Tooling
Author: Charlene Leong
Author-email: charlene.leong@relevance.ai
Requires-Python: >=3.8,<3.10
Classifier: Programming Language :: Python :: 3
Classifier: Programming Language :: Python :: 3.8
Classifier: Programming Language :: Python :: 3.9
Requires-Dist: RelevanceAI[notebook] (>=0.17.0,<0.18.0)
Requires-Dist: document-utils (>=1.3.0,<2.0.0)
Requires-Dist: numpy (>=1.21.3,<2.0.0)
Requires-Dist: pandas (>=1.3.3,<2.0.0)
Requires-Dist: plotly (>=5.3.1,<6.0.0)
Requires-Dist: scikit-learn (>=1.0,<2.0)
Requires-Dist: scipy (>=1.7.1,<2.0.0)
Requires-Dist: torch (>=1.9.1,<2.0.0)
Requires-Dist: torchvision (>=0.10.1,<0.11.0)
Requires-Dist: vectorhub[text-encoder-transformers] (>=1.8.3,<2.0.0)
